pygreensens/__init__.py
pygreensens/api.py
pygreensens-0.3.7.dist-info/LICENSE
pygreensens-0.3.7.dist-info/METADATA
pygreensens-0.3.7.dist-info/WHEEL
pygreensens-0.3.7.dist-info/top_level.txt
pygreensens-0.3.7.dist-info/RECORD
