Metadata-Version: 2.1
Name: pygreensens
Version: 0.3.7
Summary: Python package for GreenSens Plant Sensor Api
Home-page: https://github.com/pijiulaoshi/pygreensens
Author: PijiuLaoshi
Author-email: pijiulaoshi@gmail.com
License: UNKNOWN
Project-URL: Bug Tracker, https://github.com/pijiulaoshi/pygreensens/issues
Platform: UNKNOWN
Classifier: Programming Language :: Python :: 3
Classifier: License :: OSI Approved :: MIT License
Classifier: Operating System :: OS Independent
Requires-Python: >=3.6
License-File: LICENSE
